netdev/__init__.py
netdev/dispatcher.py
netdev/exceptions.py
netdev/logger.py
netdev/vendors/__init__.py
netdev/vendors/arista/__init__.py
netdev/vendors/arista/arista_eos.py
netdev/vendors/aruba/__init__.py
netdev/vendors/aruba/aruba_aos_6.py
netdev/vendors/aruba/aruba_aos_8.py
netdev/vendors/base.py
netdev/vendors/cisco/__init__.py
netdev/vendors/cisco/cisco_asa.py
netdev/vendors/cisco/cisco_ios.py
netdev/vendors/cisco/cisco_iosxr.py
netdev/vendors/cisco/cisco_nxos.py
netdev/vendors/comware_like.py
netdev/vendors/fujitsu/__init__.py
netdev/vendors/fujitsu/fujitsu_switch.py
netdev/vendors/hp/__init__.py
netdev/vendors/hp/hp_comware.py
netdev/vendors/hp/hp_comware_limited.py
netdev/vendors/infotecs/HW1000.py
netdev/vendors/infotecs/__init__.py
netdev/vendors/ios_like.py
netdev/vendors/juniper/__init__.py
netdev/vendors/juniper/juniper_junos.py
netdev/vendors/junos_like.py
netdev/vendors/mikrotik/__init__.py
netdev/vendors/mikrotik/mikrotik_routeros.py
netdev/vendors/terminal/__init__.py
netdev/vendors/terminal/terminal.py
netdev/vendors/ubiquiti/__init__.py
netdev/vendors/ubiquiti/ubiquity_edge.py
netdev/version.py
netdev-0.9.3.dist-info/LICENSE
netdev-0.9.3.dist-info/WHEEL
netdev-0.9.3.dist-info/METADATA
netdev-0.9.3.dist-info/RECORD
