Metadata-Version: 2.1
Name: netdev
Version: 0.9.3
Summary: Asynchronous multi-vendor library for interacting with network devices
Home-page: https://netdev.readthedocs.io
License: Apache-2.0
Keywords: netdev,network,netmiko,asyncio
Author: Sergey Yakovlev
Author-email: selfuryon@gmail.com
Requires-Python: >=3.6,<4.0
Classifier: Development Status :: 4 - Beta
Classifier: Framework :: AsyncIO
Classifier: Intended Audience :: Developers
Classifier: Intended Audience :: System Administrators
Classifier: Intended Audience :: Telecommunications Industry
Classifier: License :: OSI Approved :: Apache Software License
Classifier: Programming Language :: Python :: 3
Classifier: Programming Language :: Python :: 3.6
Classifier: Programming Language :: Python :: 3.7
Classifier: Topic :: System :: Networking
Classifier: Topic :: System :: Systems Administration
Provides-Extra: docs
Requires-Dist: PyYAML (>=5.1,<6.0)
Requires-Dist: asyncssh (>=1.15,<2.0)
Requires-Dist: sphinx (>=2.0,<3.0); extra == "docs"
Requires-Dist: sphinx_rtd_theme (>=0.4,<0.5); extra == "docs"
Project-URL: Documentation, https://netdev.readthedocs.io
Project-URL: Repository, https://github.com/selfuryon/netdev
